README.md
setup.cfg
setup.py
xia_pfcu/__init__.py
xia_pfcu/pfcu.py
xia_pfcu/protocol.py
xia_pfcu/simulator.py
xia_pfcu.egg-info/PKG-INFO
xia_pfcu.egg-info/SOURCES.txt
xia_pfcu.egg-info/dependency_links.txt
xia_pfcu.egg-info/entry_points.txt
xia_pfcu.egg-info/requires.txt
xia_pfcu.egg-info/top_level.txt
xia_pfcu/tango/__init__.py
xia_pfcu/tango/server/__init__.py
xia_pfcu/tango/server/pfcu.py