Metadata-Version: 2.1
Name: xia-pfcu
Version: 1.5.0
Summary: xia-pfcu library
Home-page: https://github.com/tiagocoutinho/xia-pfcu
Author: Tiago Coutinho
Author-email: tcoutinho@cells.es
License: LGPLv3+
Project-URL: Documentation, https://github.com/tiagocoutinho/xia-pfcu
Project-URL: Source, https://github.com/tiagocoutinho/xia-pfcu
Keywords: XIA,PFCU,library,tango
Platform: UNKNOWN
Classifier: Natural Language :: English
Classifier: Intended Audience :: Developers
Classifier: Development Status :: 2 - Pre-Alpha
Classifier: Programming Language :: Python :: 3
Classifier: Programming Language :: Python :: 3.5
Classifier: Programming Language :: Python :: 3.6
Classifier: Programming Language :: Python :: 3.7
Classifier: Programming Language :: Python :: 3.8
Classifier: License :: OSI Approved :: GNU Lesser General Public License v3 or later (LGPLv3+)
Provides-Extra: tango
Provides-Extra: simulator
